MANIFEST.in
README.txt
setup.py
docs/HISTORY.txt
docs/INSTALL.txt
docs/LICENSE.txt
pas/__init__.py
pas.cmfextensions.update_steps.egg-info/PKG-INFO
pas.cmfextensions.update_steps.egg-info/SOURCES.txt
pas.cmfextensions.update_steps.egg-info/dependency_links.txt
pas.cmfextensions.update_steps.egg-info/entry_points.txt
pas.cmfextensions.update_steps.egg-info/namespace_packages.txt
pas.cmfextensions.update_steps.egg-info/not-zip-safe
pas.cmfextensions.update_steps.egg-info/requires.txt
pas.cmfextensions.update_steps.egg-info/top_level.txt
pas/cmfextensions/__init__.py
pas/cmfextensions/update_steps/__init__.py
pas/cmfextensions/update_steps/configure.zcml
pas/cmfextensions/update_steps/handlers.py
pas/cmfextensions/update_steps/quick_installer.py