Metadata-Version: 1.0
Name: pas.cmfextensions.update-steps
Version: 0.1
Summary: .
Home-page: https://www.smile-suisse.com
Author: Maric Michaud
Author-email: maric.michaud@smile-suisse.com
License: GPL
Keywords: PluggableAuthService GenericSetup
Platform: UNKNOWN
Classifier: Development Status :: 4 - Beta
Classifier: Framework :: Zope2
Classifier: Programming Language :: Python
Classifier: License :: OSI Approved :: GNU General Public License v3 or later (GPLv3+)
Classifier: Operating System :: OS Independent
